alfresco_mcp_server/__init__.py
alfresco_mcp_server/config.py
alfresco_mcp_server/fastmcp_server.py
alfresco_mcp_server/prompts/__init__.py
alfresco_mcp_server/prompts/search_and_analyze.py
alfresco_mcp_server/resources/__init__.py
alfresco_mcp_server/resources/repository_resources.py
alfresco_mcp_server/tools/__init__.py
alfresco_mcp_server/tools/core/__init__.py
alfresco_mcp_server/tools/core/browse_repository.py
alfresco_mcp_server/tools/core/cancel_checkout.py
alfresco_mcp_server/tools/core/checkin_document.py
alfresco_mcp_server/tools/core/checkout_document.py
alfresco_mcp_server/tools/core/create_folder.py
alfresco_mcp_server/tools/core/delete_node.py
alfresco_mcp_server/tools/core/download_document.py
alfresco_mcp_server/tools/core/get_node_properties.py
alfresco_mcp_server/tools/core/update_node_properties.py
alfresco_mcp_server/tools/core/upload_document.py
alfresco_mcp_server/tools/search/__init__.py
alfresco_mcp_server/tools/search/advanced_search.py
alfresco_mcp_server/tools/search/cmis_search.py
alfresco_mcp_server/tools/search/search_by_metadata.py
alfresco_mcp_server/tools/search/search_content.py
alfresco_mcp_server/utils/__init__.py
alfresco_mcp_server/utils/connection.py
alfresco_mcp_server/utils/file_type_analysis.py
alfresco_mcp_server/utils/json_utils.py
python_alfresco_mcp_server-1.1.0.dist-info/licenses/LICENSE
python_alfresco_mcp_server-1.1.0.dist-info/METADATA
python_alfresco_mcp_server-1.1.0.dist-info/WHEEL
python_alfresco_mcp_server-1.1.0.dist-info/entry_points.txt
python_alfresco_mcp_server-1.1.0.dist-info/top_level.txt
python_alfresco_mcp_server-1.1.0.dist-info/RECORD
