Metadata-Version: 2.4
Name: python-alfresco-mcp-server
Version: 1.1.0
Summary: FastMCP 2.0 server for Alfresco Content Services integration
Author-email: Steve Reiner <example@example.com>
License: Apache-2.0
Project-URL: Homepage, https://github.com/stevereiner/python-alfresco-mcp-server
Project-URL: Repository, https://github.com/stevereiner/python-alfresco-mcp-server
Project-URL: Issues, https://github.com/stevereiner/python-alfresco-mcp-server/issues
Project-URL: Documentation, https://github.com/stevereiner/python-alfresco-mcp-server#readme
Keywords: alfresco,mcp,content-management,fastmcp,ai
Classifier: Development Status :: 4 - Beta
Classifier: Intended Audience :: Developers
Classifier: License :: OSI Approved :: Apache Software License
Classifier: Programming Language :: Python :: 3
Classifier: Programming Language :: Python :: 3.10
Classifier: Programming Language :: Python :: 3.11
Classifier: Programming Language :: Python :: 3.12
Classifier: Programming Language :: Python :: 3.13
Classifier: Topic :: Software Development :: Libraries :: Python Modules
Classifier: Topic :: Internet :: WWW/HTTP :: Dynamic Content :: Content Management System
Classifier: Topic :: Internet :: WWW/HTTP :: Indexing/Search
Classifier: Topic :: Database :: Database Engines/Servers
Classifier: Topic :: Scientific/Engineering :: Artificial Intelligence
Requires-Python: >=3.10
License-File: LICENSE
Requires-Dist: fastmcp>=2.9.0
Requires-Dist: python-alfresco-api>=1.1.1
Requires-Dist: pydantic>=2.0.0
Requires-Dist: pydantic-settings>=2.0.0
Requires-Dist: PyYAML>=6.0
Requires-Dist: httpx>=0.24.0
Requires-Dist: python-multipart>=0.0.6
Provides-Extra: dev
Requires-Dist: black>=23.0.0; extra == "dev"
Requires-Dist: ruff>=0.1.0; extra == "dev"
Requires-Dist: mypy>=1.0.0; extra == "dev"
Provides-Extra: test
Requires-Dist: pytest>=7.0.0; extra == "test"
Requires-Dist: pytest-asyncio>=0.21.0; extra == "test"
Requires-Dist: pytest-cov>=4.0.0; extra == "test"
Requires-Dist: pytest-xdist>=3.0.0; extra == "test"
Requires-Dist: pytest-mock>=3.10.0; extra == "test"
Requires-Dist: coverage[toml]>=7.0.0; extra == "test"
Requires-Dist: httpx>=0.24.0; extra == "test"
Provides-Extra: all
Requires-Dist: python-alfresco-mcp-server[dev]; extra == "all"
Requires-Dist: python-alfresco-mcp-server[test]; extra == "all"
Dynamic: license-file
